{
  "customerList": [
    {
      "id": 1,
      "organization": "1",
      "contactFace": "",
      "phone": "",
      "email": "",
      "description": "",
      "reminder": false,
      "reminderDate": "2023-05-14T09:37:42.041Z"
    },
    {
      "id": 2,
      "organization": "2",
      "contactFace": "",
      "phone": "",
      "email": "",
      "description": "",
      "reminder": false,
      "reminderDate": "2023-05-14T09:37:56.345Z"
    },
    {
      "id": 3,
      "organization": "3",
      "contactFace": "",
      "phone": "",
      "email": "",
      "description": "",
      "reminder": false,
      "reminderDate": "2023-05-14T09:38:06.558Z"
    }
  ]
}